dlmdutils-0.1.data/data/requirements.txt
hooks/__init__.py
hooks/checkpoint_hook.py
hooks/distributed_hook.py
hooks/eval_hook.py
hooks/hookbase.py
hooks/logger_hook.py
hooks/lr_update_hook.py
dlmdutils-0.1.dist-info/METADATA
dlmdutils-0.1.dist-info/WHEEL
dlmdutils-0.1.dist-info/top_level.txt
dlmdutils-0.1.dist-info/RECORD
